odoo/addons/sm_partago_usage/__init__.py
odoo/addons/sm_partago_usage/__manifest__.py
odoo/addons/sm_partago_usage/models/__init__.py
odoo/addons/sm_partago_usage/models/models_sm_member.py
odoo/addons/sm_partago_usage/models/models_smp_edit_reservation_compute_wizard.py
odoo/addons/sm_partago_usage/models/models_smp_reservation_compute.py
odoo/addons/sm_partago_usage/models/models_smp_reservation_wizard.py
odoo/addons/sm_partago_usage/models/models_smp_usage_cron.py
odoo/addons/sm_partago_usage/models/models_smp_usage_utils.py
odoo/addons/sm_partago_usage/security/ir.model.access.csv
odoo/addons/sm_partago_usage/views/views.xml
odoo/addons/sm_partago_usage/views/views_cron.xml
odoo/addons/sm_partago_usage/views/views_edit_reservation_compute_wizard.xml
odoo/addons/sm_partago_usage/views/views_members.xml
odoo/addons/sm_partago_usage/views/views_reservation_compute.xml
odoo/addons/sm_partago_usage/views/views_wizards.xml
odoo12_addon_sm_partago_usage-12.0.0.1.13.dist-info/METADATA
odoo12_addon_sm_partago_usage-12.0.0.1.13.dist-info/WHEEL
odoo12_addon_sm_partago_usage-12.0.0.1.13.dist-info/top_level.txt
odoo12_addon_sm_partago_usage-12.0.0.1.13.dist-info/RECORD
