Metadata-Version: 2.1
Name: odoo12-addon-sm-partago-usage
Version: 12.0.0.1.13
Summary: Module to manage reservations from booking app
Home-page: https://www.sommobilitat.coop
Author: Som Mobilitat
License: UNKNOWN
Platform: UNKNOWN
Classifier: Programming Language :: Python
Classifier: Framework :: Odoo
Classifier: Framework :: Odoo :: 12.0
Requires-Python: >=3.5
Requires-Dist: odoo12-addon-sm-carsharing-structure
Requires-Dist: odoo12-addon-vertical-carsharing
Requires-Dist: odoo <12.1dev,>=12.0a
